cotohacall/__init__.py
cotohacall/cotohacall.py
cotohacall/main.py
cotohacall/test_cotohacall.py
cotohacall/test_main.py
Cotoha_at_python-2.0.dist-info/METADATA
Cotoha_at_python-2.0.dist-info/WHEEL
Cotoha_at_python-2.0.dist-info/top_level.txt
Cotoha_at_python-2.0.dist-info/RECORD
