Metadata-Version: 2.1
Name: Cotoha-at-python
Version: 2.0
Summary: Make it easy to use Japanese processing API, Cotoha.
Home-page: https://github.com/TOOOOOOMY/Cotoha_at_python
Author: TOOOOOOMY
Author-email: 10talatgi@gmail.com
License: MIT
